tapeagents/__init__.py
tapeagents/agent.py
tapeagents/batch.py
tapeagents/config.py
tapeagents/core.py
tapeagents/demo.py
tapeagents/dialog_tape.py
tapeagents/environment.py
tapeagents/io.py
tapeagents/llm_function.py
tapeagents/mcp.py
tapeagents/nodes.py
tapeagents/observe.py
tapeagents/optimize.py
tapeagents/orchestrator.py
tapeagents/parallel_processing.py
tapeagents/prompting.py
tapeagents/remote_environment.py
tapeagents/steps.py
tapeagents/studio.py
tapeagents/tape_browser.py
tapeagents/team.py
tapeagents/tool_calling.py
tapeagents/utils.py
tapeagents/view.py
tapeagents/finetune/__init__.py
tapeagents/finetune/checkpoints.py
tapeagents/finetune/context.py
tapeagents/finetune/data.py
tapeagents/finetune/eval.py
tapeagents/finetune/finetune.py
tapeagents/finetune/logging_.py
tapeagents/finetune/lora.py
tapeagents/finetune/optim.py
tapeagents/finetune/types.py
tapeagents/finetune/rl/__init__.py
tapeagents/finetune/rl/utils.py
tapeagents/llms/__init__.py
tapeagents/llms/base.py
tapeagents/llms/cached.py
tapeagents/llms/claude.py
tapeagents/llms/lite.py
tapeagents/llms/mock.py
tapeagents/llms/replay.py
tapeagents/llms/trainable.py
tapeagents/renderers/__init__.py
tapeagents/renderers/basic.py
tapeagents/renderers/camera_ready_renderer.py
tapeagents/renderers/pretty.py
tapeagents/tools/__init__.py
tapeagents/tools/base.py
tapeagents/tools/browser.py
tapeagents/tools/calculator.py
tapeagents/tools/code_executor.py
tapeagents/tools/container_executor.py
tapeagents/tools/converters.py
tapeagents/tools/document_reader.py
tapeagents/tools/grounding.py
tapeagents/tools/media_reader.py
tapeagents/tools/memory.py
tapeagents/tools/simple_browser.py
tapeagents/tools/stock.py
tapeagents/tools/tool_cache.py
tapeagents/tools/web_search.py
tapeagents/tools/computer/Dockerfile
tapeagents/tools/computer/__init__.py
tapeagents/tools/computer/__main__.py
tapeagents/tools/computer/api.py
tapeagents/tools/computer/computer.py
tapeagents/tools/computer/steps.py
tapeagents-0.1.16.dist-info/METADATA
tapeagents-0.1.16.dist-info/WHEEL
tapeagents-0.1.16.dist-info/licenses/LICENSE
tapeagents-0.1.16.dist-info/licenses/NOTICE
tapeagents-0.1.16.dist-info/RECORD
