Metadata-Version: 2.4
Name: TapeAgents
Version: 0.1.16
Summary: TapeAgents framework for building, tuning and evaluating LLM Agents
Project-URL: GitHub, https://github.com/ServiceNow/TapeAgents
Author: Dzmitry Bahdanau, Oleh Shliazhko, Alexandre Piché, Jordan Prince Tremblay
License: Apache-2.0
License-File: LICENSE
License-File: NOTICE
Classifier: Development Status :: 4 - Beta
Classifier: Intended Audience :: Science/Research
Classifier: License :: OSI Approved :: Apache Software License
Classifier: Operating System :: OS Independent
Classifier: Programming Language :: Python :: 3
Classifier: Topic :: Scientific/Engineering :: Artificial Intelligence
Requires-Python: <3.13,>=3.10
Requires-Dist: aiofiles>=23.2.1
Requires-Dist: anthropic>=0.49.0
Requires-Dist: browsergym~=0.13
Requires-Dist: coverage>=7.6.12
Requires-Dist: fastapi~=0.115
Requires-Dist: flameprof>=0.4
Requires-Dist: gradio~=5.11
Requires-Dist: hydra-core~=1.3
Requires-Dist: jsonref~=1.1
Requires-Dist: langchain-community~=0.3
Requires-Dist: langchain-core~=0.1
Requires-Dist: levenshtein~=0.25
Requires-Dist: litellm~=1.61
Requires-Dist: mcp>=1.9.0
Requires-Dist: nest-asyncio>=1.6.0
Requires-Dist: openai~=1.55
Requires-Dist: pathvalidate~=3.2
Requires-Dist: playwright~=1.42
Requires-Dist: podman~=5.0
Requires-Dist: pyautogui>=0.9.54
Requires-Dist: pydantic~=2.9
Requires-Dist: pytest-asyncio>=0.26.0
Requires-Dist: pytest-cov>=6.0.0
Requires-Dist: pytest-xdist>=3.6.1
Requires-Dist: pyyaml~=6.0
Requires-Dist: streamlit>=1.42.0
Requires-Dist: tavily-python~=0.3
Requires-Dist: termcolor~=2.4
Requires-Dist: tqdm~=4.66
Provides-Extra: converters
Requires-Dist: beautifulsoup4~=4.12; extra == 'converters'
Requires-Dist: docling~=2.28.0; extra == 'converters'
Requires-Dist: easyocr~=1.7; extra == 'converters'
Requires-Dist: ffmpeg-python~=0.2; extra == 'converters'
Requires-Dist: lxml[html-clean]~=5.2; extra == 'converters'
Requires-Dist: mammoth~=1.8; extra == 'converters'
Requires-Dist: markdownify~=0.13; extra == 'converters'
Requires-Dist: openai-whisper>=20240930; extra == 'converters'
Requires-Dist: openpyxl~=3.1; extra == 'converters'
Requires-Dist: pandas~=2.2; extra == 'converters'
Requires-Dist: pdf2image~=1.17; extra == 'converters'
Requires-Dist: pdfminer-six>=20240706; extra == 'converters'
Requires-Dist: puremagic~=1.26; extra == 'converters'
Requires-Dist: pydub~=0.25; extra == 'converters'
Requires-Dist: pyparsing~=3.1; extra == 'converters'
Requires-Dist: python-pptx~=1.0.2; extra == 'converters'
Requires-Dist: readability-lxml>=0.8; extra == 'converters'
Requires-Dist: webvtt-py~=0.5; extra == 'converters'
Requires-Dist: xlrd~=2.0; extra == 'converters'
Requires-Dist: youtube-transcript-api~=0.6; extra == 'converters'
Requires-Dist: yt-dlp>=2024.12.13; extra == 'converters'
Provides-Extra: finetune
Requires-Dist: accelerate~=1.7.0; extra == 'finetune'
Requires-Dist: datasets~=2.21; extra == 'finetune'
Requires-Dist: deepspeed~=0.15.4; extra == 'finetune'
Requires-Dist: numpy~=1.26; extra == 'finetune'
Requires-Dist: peft==0.12; extra == 'finetune'
Requires-Dist: transformers~=4.51.0; extra == 'finetune'
Requires-Dist: wandb~=0.19; extra == 'finetune'
Provides-Extra: rl-gsm8k
Requires-Dist: vllm<=0.6.6.post1,>=0.5.3; extra == 'rl-gsm8k'
